Metadata-Version: 2.1
Name: tibetan_sort
Version: 0.2.0
Summary: Tibetan Sorting Tool
Home-page: https://github.com/Esukhia/tibetan-sort-python
Author: Esukhia development team
Author-email: esukhiadev@gmail.com
License: Apache2
Project-URL: Source, https://github.com/Esukhia/tibetan-sort-python
Project-URL: Tracker, https://github.com/Esukhia/tibetan-sort-python/issues
Keywords: nlp computational_linguistics tibetan sort
Platform: UNKNOWN
Classifier: Development Status :: 3 - Alpha
Classifier: Topic :: Text Processing :: Linguistic
Classifier: Programming Language :: Python :: 3
Classifier: Operating System :: OS Independent
Classifier: Intended Audience :: Developers
Classifier: Intended Audience :: Science/Research
Classifier: License :: OSI Approved :: Apache Software License
Classifier: Natural Language :: Tibetan
Requires-Python: >=3.6
